captacity_clipify/__init__.py
captacity_clipify/cli.py
captacity_clipify/segment_parser.py
captacity_clipify/text_drawer.py
captacity_clipify/transcriber.py
captacity_clipify/assets/fonts/Bangers-Regular-LICENSE.txt
captacity_clipify/assets/fonts/Bangers-Regular.ttf
captacity_clipify/assets/fonts/Knewave-Regular-LICENSE.txt
captacity_clipify/assets/fonts/Knewave-Regular.ttf
captacity_clipify/assets/fonts/PoetsenOne-Regular-LICENSE.txt
captacity_clipify/assets/fonts/PoetsenOne-Regular.ttf
captacity_clipify-0.3.4.dist-info/LICENSE
captacity_clipify-0.3.4.dist-info/METADATA
captacity_clipify-0.3.4.dist-info/WHEEL
captacity_clipify-0.3.4.dist-info/entry_points.txt
captacity_clipify-0.3.4.dist-info/top_level.txt
captacity_clipify-0.3.4.dist-info/RECORD
